cape/__init__.py
cape/version.py
cape/client/__init__.py
cape/client/client.py
cape/client/exceptions.py
cape/client/utils.py
cape/client/version.py
cape_client-0.2.0.dist-info/DESCRIPTION.rst
cape_client-0.2.0.dist-info/METADATA
cape_client-0.2.0.dist-info/RECORD
cape_client-0.2.0.dist-info/WHEEL
cape_client-0.2.0.dist-info/metadata.json
cape_client-0.2.0.dist-info/top_level.txt
