Metadata-Version: 2.0
Name: cape-client
Version: 0.2.0
Summary: Client library for the Cape machine reading API
Home-page: https://github.com/bloomsburyai/cape-client
Author: Bloomsbury AI
Author-email: contact@bloomsbury.ai
License: MIT
Keywords: ai nlp natural language question answer chat chatbot bot artificial intelligence
Platform: UNKNOWN
Classifier: Development Status :: 3 - Alpha
Classifier: Intended Audience :: Developers
Classifier: Intended Audience :: Science/Research
Classifier: License :: OSI Approved :: MIT License
Classifier: Programming Language :: Python :: 3
Classifier: Programming Language :: Python :: 3.5
Classifier: Programming Language :: Python :: 3.6
Classifier: Topic :: Communications :: Chat
Classifier: Topic :: Scientific/Engineering :: Artificial Intelligence
Classifier: Topic :: Text Processing :: Linguistic
Requires-Python: >=3.5
Requires-Dist: requests (>=2.18.1)
Requires-Dist: requests-toolbelt (>=0.8.0)
